LICENSE.md
MANIFEST.in
README.md
requirements.txt
setup.py
mapula/__init__.py
mapula/bio.py
mapula/const.py
mapula/count.py
mapula/main.py
mapula/merge.py
mapula/observation.py
mapula/utils.py
mapula.egg-info/PKG-INFO
mapula.egg-info/SOURCES.txt
mapula.egg-info/dependency_links.txt
mapula.egg-info/entry_points.txt
mapula.egg-info/not-zip-safe
mapula.egg-info/requires.txt
mapula.egg-info/top_level.txt