Metadata-Version: 2.1
Name: mapula
Version: 2.1.1
Summary: Calculation of alignment statistics
Home-page: https://github.com/epi2me-labs/mapula
Author: epi2melabs
Author-email: epi2melabs@nanoporetech.com
License: UNKNOWN
Platform: UNKNOWN
